unified_planning/__init__.py
unified_planning/environment.py
unified_planning/exceptions.py
unified_planning/shortcuts.py
unified_planning/utils.py
unified_planning/cmd/__init__.py
unified_planning/cmd/arg_parser.py
unified_planning/cmd/up.py
unified_planning/engines/__init__.py
unified_planning/engines/credits.py
unified_planning/engines/engine.py
unified_planning/engines/factory.py
unified_planning/engines/meta_engine.py
unified_planning/engines/oversubscription_planner.py
unified_planning/engines/parallel.py
unified_planning/engines/pddl_anytime_planner.py
unified_planning/engines/pddl_planner.py
unified_planning/engines/plan_validator.py
unified_planning/engines/replanner.py
unified_planning/engines/results.py
unified_planning/engines/sequential_simulator.py
unified_planning/engines/compilers/__init__.py
unified_planning/engines/compilers/bounded_types_remover.py
unified_planning/engines/compilers/compilers_pipeline.py
unified_planning/engines/compilers/conditional_effects_remover.py
unified_planning/engines/compilers/disjunctive_conditions_remover.py
unified_planning/engines/compilers/grounder.py
unified_planning/engines/compilers/ma_conditional_effects_remover.py
unified_planning/engines/compilers/ma_disjunctive_conditions_remover.py
unified_planning/engines/compilers/negative_conditions_remover.py
unified_planning/engines/compilers/quantifiers_remover.py
unified_planning/engines/compilers/state_invariants_remover.py
unified_planning/engines/compilers/tarski_grounder.py
unified_planning/engines/compilers/trajectory_constraints_remover.py
unified_planning/engines/compilers/usertype_fluents_remover.py
unified_planning/engines/compilers/utils.py
unified_planning/engines/mixins/__init__.py
unified_planning/engines/mixins/anytime_planner.py
unified_planning/engines/mixins/compiler.py
unified_planning/engines/mixins/oneshot_planner.py
unified_planning/engines/mixins/plan_repairer.py
unified_planning/engines/mixins/plan_validator.py
unified_planning-1.2.0.dist-info/LICENSE
unified_planning-1.2.0.dist-info/METADATA
unified_planning-1.2.0.dist-info/WHEEL
unified_planning-1.2.0.dist-info/entry_points.txt
unified_planning-1.2.0.dist-info/top_level.txt
unified_planning-1.2.0.dist-info/RECORD
