Metadata-Version: 2.1
Name: unified_planning
Version: 1.2.0
Summary: Unified Planning Framework
Home-page: https://www.aiplan4eu-project.eu
Author: AIPlan4EU Project
Author-email: aiplan4eu@fbk.eu
License: APACHE
Keywords: planning logic STRIPS RDDL
Classifier: Development Status :: 3 - Alpha
Classifier: Intended Audience :: Science/Research
Classifier: Intended Audience :: Developers
Classifier: Topic :: Scientific/Engineering :: Artificial Intelligence
Classifier: License :: OSI Approved :: Apache Software License
Classifier: Programming Language :: Python :: 3.8
Classifier: Programming Language :: Python :: 3.9
Classifier: Programming Language :: Python :: 3.10
Classifier: Programming Language :: Python :: 3.11
Requires-Python: >=3.8
Provides-Extra: dev
Provides-Extra: grpc
Provides-Extra: tarski
Provides-Extra: pyperplan
Provides-Extra: tamer
Provides-Extra: enhsp
Provides-Extra: fast-downward
Provides-Extra: lpg
Provides-Extra: fmap
Provides-Extra: aries
Provides-Extra: symk
Provides-Extra: engines
Provides-Extra: plot
License-File: LICENSE
